<annotation>
	<folder>Training</folder>
	<filename>hairClip_3.jpg</filename>
	<path>/Users/huyennguyen/Huyen/GitHub/VAST2020mc2/Training/hairClip_3.jpg</path>
	<source>
		<database>Unknown</database>
	</source>
	<size>
		<width>5184</width>
		<height>3456</height>
		<depth>3</depth>
	</size>
	<segmented>0</segmented>
	<object>
		<name>hairClip</name>
		<pose>Unspecified</pose>
		<truncated>0</truncated>
		<difficult>0</difficult>
		<bndbox>
			<xmin>2147</xmin>
			<ymin>946</ymin>
			<xmax>3043</xmax>
			<ymax>1871</ymax>
		</bndbox>
	</object>
</annotation>
